architex/__init__.py
architex/__main__.py
architex/controller.py
architex/view.py
architex-0.1.8.dist-info/WHEEL
architex-0.1.8.dist-info/METADATA
architex-0.1.8.dist-info/RECORD
